posthog_agent_toolkit/__init__.py
posthog_agent_toolkit/integrations/__init__.py
posthog_agent_toolkit/integrations/langchain/__init__.py
posthog_agent_toolkit/integrations/langchain/toolkit.py
posthog_agent_toolkit-0.1.2.dist-info/METADATA
posthog_agent_toolkit-0.1.2.dist-info/WHEEL
posthog_agent_toolkit-0.1.2.dist-info/RECORD
