Metadata-Version: 2.4
Name: posthog-agent-toolkit
Version: 0.1.2
Summary: PostHog Agent Toolkit for LangChain and other AI frameworks
Author-email: PostHog <hey@posthog.com>
Requires-Python: >=3.11
Requires-Dist: httpx>=0.25.0
Requires-Dist: langchain-core>=0.1.0
Requires-Dist: langchain-mcp-adapters>=0.1.0
Requires-Dist: pydantic>=2.5.0
Requires-Dist: python-dateutil>=2.8.2
Requires-Dist: python-dotenv>=1.0.0
Requires-Dist: typing-extensions>=4.8.0
